find_palindroms/__about__.py
find_palindroms/__init__.py
find_palindroms/__main__.py
find_palindroms/__test__.py
find_palindroms/find_palindrom.py
find_palindroms-0.1.dist-info/LICENSE.txt
find_palindroms-0.1.dist-info/METADATA
find_palindroms-0.1.dist-info/WHEEL
find_palindroms-0.1.dist-info/entry_points.txt
find_palindroms-0.1.dist-info/top_level.txt
find_palindroms-0.1.dist-info/RECORD
