Metadata-Version: 2.1
Name: find_palindroms
Version: 0.1
Summary: find palindroms
Author: leon.need
Author-email: leon.need08@yandex.ru
License: MIT License
Requires-Python: >=3.5
License-File: LICENSE.txt
